yc_secret/__init__.py
yc_secret/__version__.py
yc_secret/exception.py
yc_secret/secret.py
yc_secret-0.1.2.dist-info/LICENSE
yc_secret-0.1.2.dist-info/METADATA
yc_secret-0.1.2.dist-info/WHEEL
yc_secret-0.1.2.dist-info/top_level.txt
yc_secret-0.1.2.dist-info/RECORD
